dogbolt_cli/__init__.py
dogbolt_cli-0.1.4.dist-info/LICENSE
dogbolt_cli-0.1.4.dist-info/METADATA
dogbolt_cli-0.1.4.dist-info/WHEEL
dogbolt_cli-0.1.4.dist-info/entry_points.txt
dogbolt_cli-0.1.4.dist-info/top_level.txt
dogbolt_cli-0.1.4.dist-info/RECORD
