Metadata-Version: 2.2
Name: dogbolt-cli
Version: 0.1.4
Summary: A CLI for Dogbolt. Uploads your binary and downloads decompiled source code.
Author-email: itachichrist <itachichrist@gmail.com>, Jacek Wielemborek <gh@d33.pl>
License: MIT
License-File: LICENSE
Requires-Dist: requests
